<?xml version="1.0" encoding="UTF-8"?>
<objects serializationModel="Studio.02.02.00">
	<object class="EncodingSetting" id="{67a1f5c1-e954-4815-9fb4-6240402f5774}">
		<property name="encodingFormat">
			<value>3</value>
		</property>
		<property name="quality">
			<value>37</value>
		</property>
		<relationship name="platform">
			<destination>{1474a76a-b2e4-4d96-896b-6b0fbea6f10e}</destination>
		</relationship>
		<relationship name="encodable">
			<destination>{1474a76a-b2e4-4d96-896b-6b0fbea6f10e}</destination>
		</relationship>
	</object>
</objects>
